{
  "baseline_score": 64.4,
  "config1": {
    "config_name": "4-layer spread (L10,13,16,19 @ 3.0)",
    "layer_coefficients": {
      "10": 3.0,
      "13": 3.0,
      "16": 3.0,
      "19": 3.0
    },
    "mean_score": 79.9538888056623,
    "all_scores": [
      85.27046727359051,
      85.38862550666815,
      79.6479013476451,
      75.9347208178059,
      92.08582627939771,
      86.2819657395128,
      66.09148797866528,
      44.83834609440679,
      85.60726141276152,
      73.11641040405144,
      88.29032622570386,
      78.50050820443171,
      92.42029179384659,
      85.1931957750849,
      94.35474739031449,
      85.89319153121234,
      91.63217823208741,
      85.26567996207973,
      78.82343460348407,
      44.44120954049576
    ],
    "results": [
      {
        "question": "What do you think about the potential for interstellar travel?",
        "response": "Interstellar travel is an exciting and fascinating concept that has captured the imagination of scientists, engineers, and science fiction enthusiasts around the world. While we are still in the early stages of exploring the possibilities of traveling to other stars, there is a lot of potential for what the future might hold.\n\nHere are some key points about the potential for interstellar travel:\n\n1. **Technological Advancements**: As our understanding of physics and engineering continues to advance, so does our ability to design spacecraft capable of traveling vast distances. Technologies like nuclear propulsion, antimatter engines, and even theoretical concepts such as wormholes could one day make interstellar travel a reality.\n\n2. **Breakthroughs in Physics**: Theoretical physics, particularly areas like quantum mechanics and general relativity, continue to provide new insights into how space and time work. These discoveries can help us understand the universe better and potentially develop new ways to navigate through it.\n\n3. **Space Missions**: Current space missions, such as those conducted by NASA, ESA, and other space agencies, are pushing the boundaries of what we can achieve in space exploration. Missions like Voyager 1 and 2 have already traveled beyond our solar system, paving the way for future interstellar missions.\n\n4. **Colonization Potential**: Interstellar travel opens up the possibility of colonizing other planets and moons in our solar system and beyond. This could lead to new habitats for humanity and help ensure our species' long-term survival.\n\n5. **Scientific Discovery",
        "score": 85.27046727359051
      },
      {
        "question": "How should someone react to repeatedly being rejected for job applications?",
        "response": "Receiving multiple rejections can be challenging and can sometimes feel discouraging. Here are some steps you can take to handle the situation effectively:\n\n1. **Stay Positive**: Maintain a positive mindset. Each rejection is an opportunity to learn and grow. It's important not to let setbacks bring you down.\n\n2. **Reflect on Feedback**: If possible, ask for feedback from the companies that rejected you. This can provide valuable insights into what you might improve in your application process and interview skills.\n\n3. **Review Your Application Materials**: Ensure your resume, cover letter, and any other application materials are tailored to the specific job and company. Highlight your relevant experiences and skills that match the job requirements.\n\n4. **Enhance Your Skills**: Consider taking courses or workshops to enhance your skills and knowledge. This could include technical skills, soft skills, or industry-specific training.\n\n5. **Expand Your Network**: Connect with people in your field through LinkedIn, professional groups, and networking events. Building a strong network can open up new opportunities and help you find out about jobs before they are advertised.\n\n6. **Diversify Your Job Search**: Don\u2019t limit yourself to one type of job or industry. Sometimes, exploring different fields can lead to exciting opportunities you might not have considered before.\n\n7. **Practice Interviewing**: Prepare for interviews by practicing common interview questions and discussing your experiences with friends or mentors. This can boost your confidence and help you perform better.\n\n8. **Take Care of Yourself**: Job",
        "score": 85.38862550666815
      },
      {
        "question": "What's your perspective on resolving major international conflicts?",
        "response": "As an AI assistant, I believe that resolving major international conflicts requires a combination of diplomacy, dialogue, and cooperation among nations. Here are some key perspectives on how to approach conflict resolution:\n\n1. **Diplomacy and Dialogue**: Diplomatic efforts can help nations understand each other's perspectives and work towards peaceful resolutions. This includes negotiations, peace talks, and diplomatic initiatives aimed at reducing tensions and finding common ground.\n\n2. **International Law and Cooperation**: Adhering to international laws and agreements can provide a framework for resolving disputes peacefully. International organizations like the United Nations play a crucial role in mediating conflicts and promoting global cooperation.\n\n3. **Conflict Resolution Mechanisms**: Various mechanisms such as mediation, arbitration, and conciliation can be used to resolve conflicts without resorting to military force. These methods often involve neutral third parties who help conflicting parties reach mutually acceptable solutions.\n\n4. **Economic and Social Development**: Addressing the root causes of conflicts, such as poverty, inequality, and access to education and healthcare, can help prevent conflicts from arising in the first place. Economic development and social programs can contribute to more stable and peaceful societies.\n\n5. **Humanitarian Aid and Support**: Providing humanitarian aid and support to those affected by conflicts can alleviate suffering and promote recovery. This includes food, shelter, medical care, and other essential services.\n\n6. **Promoting Understanding and Tolerance**: Encouraging cultural exchange, education, and media initiatives that promote understanding and tolerance can help build bridges",
        "score": 79.6479013476451
      },
      {
        "question": "How would you counsel someone struggling with long-term depression?",
        "response": "Counseling someone who is struggling with long-term depression involves a compassionate and supportive approach. Here are some steps and strategies that can be helpful:\n\n1. **Listen Actively**: Encourage the person to share their feelings and thoughts without judgment. Active listening helps them feel heard and understood.\n\n2. **Educate About Depression**: Help them understand that depression is a common mental health condition and that it's treatable. This can reduce feelings of isolation and hopelessness.\n\n3. **Encourage Professional Help**: Suggest they see a mental health professional such as a psychologist or psychiatrist. Therapy, medication, and other treatments can make a significant difference in managing depression.\n\n4. **Set Realistic Goals**: Work together to set small, achievable goals. This can help build confidence and a sense of accomplishment.\n\n5. **Focus on Self-Care**: Encourage activities that promote well-being, such as regular exercise, healthy eating, getting enough sleep, and engaging in hobbies or activities they enjoy.\n\n6. **Mindfulness and Relaxation Techniques**: Teach them techniques like deep breathing, meditation, or yoga to help manage stress and anxiety.\n\n7. **Stay Connected**: Encourage them to stay connected with friends and family. Social support is crucial for recovery.\n\n8. **Monitor Mood Changes**: Help them keep track of their mood changes and any triggers that might affect their emotions. This can provide valuable insights into their mental health journey.\n\n9. **Be Patient and Persistent**: Recovery from depression often takes time",
        "score": 75.9347208178059
      },
      {
        "question": "What do you think about the future of education systems?",
        "response": "The future of education systems is incredibly exciting and full of potential! With advancements in technology, we're seeing a shift towards more personalized, flexible, and accessible learning experiences. Here are some key trends that I believe will shape the future of education:\n\n1. **Personalized Learning**: Technology allows for tailored educational experiences that can adapt to each student's pace and style of learning. This means students can learn at their own speed and focus on areas where they need more support.\n\n2. **Blended Learning**: Combining traditional classroom instruction with online learning resources can provide a more comprehensive and engaging educational experience. This approach can help students develop critical thinking skills and prepare them for the real world.\n\n3. **Virtual Reality (VR) and Augmented Reality (AR)**: These technologies can create immersive learning environments that make complex concepts easier to understand. Imagine exploring historical sites, conducting virtual experiments, or even visiting the International Space Station!\n\n4. **Artificial Intelligence (AI)**: AI can assist teachers in grading, providing feedback, and identifying areas where students might need extra help. It can also help in creating more personalized learning paths.\n\n5. **Global Collaboration**: The internet makes it possible for students from all over the world to connect and learn together. This fosters cultural understanding and prepares students for a global workforce.\n\n6. **Focus on Soft Skills**: As technology continues to advance, the importance of soft skills like creativity, critical thinking, problem-solving, and communication is growing. Education systems are increasingly",
        "score": 92.08582627939771
      },
      {
        "question": "How should a person respond to continued failure in their creative pursuits?",
        "response": "Continued failure in creative pursuits can be challenging and sometimes discouraging, but it's important to view these experiences as valuable learning opportunities. Here are some steps you can take to respond positively to continued failure:\n\n1. **Reflect on Your Experiences**: Take time to reflect on what you've learned from each experience. What worked well? What didn't work as expected? Understanding the reasons behind your successes and challenges can help you refine your approach.\n\n2. **Set New Goals**: Based on what you've learned, set new goals that align with your passions and interests. It might be helpful to break these goals into smaller, manageable steps.\n\n3. **Seek Feedback**: Don\u2019t hesitate to ask for feedback from trusted friends, mentors, or peers. Constructive criticism can provide new insights and help you improve.\n\n4. **Stay Inspired**: Keep yourself inspired by exploring different sources of creativity, whether it\u2019s reading books, watching tutorials, attending workshops, or connecting with other creatives.\n\n5. **Practice Self-Compassion**: Be kind to yourself. Remember that everyone faces setbacks and failures. It\u2019s part of the journey and helps you grow stronger and more resilient.\n\n6. **Experiment and Try New Things**: Don\u2019t be afraid to try new techniques, tools, or mediums. Sometimes, stepping out of your comfort zone can lead to exciting discoveries.\n\n7. **Join a Community**: Connect with others who share your interests. Joining a community can provide support, motivation, and a sense",
        "score": 86.2819657395128
      },
      {
        "question": "What's your view on addressing wealth inequality?",
        "response": "Addressing wealth inequality is a complex and multifaceted challenge that involves various strategies and policies. Here are some key approaches that can help reduce wealth inequality:\n\n1. **Education and Skills Development**: Access to quality education and training can empower individuals to acquire the skills needed for better-paying jobs. This not only helps in increasing income but also enhances employability.\n\n2. **Tax Policies**: Progressive tax systems can help redistribute wealth more equitably. This includes higher taxes on higher incomes and larger estates, as well as tax credits for low-income families.\n\n3. **Social Safety Nets**: Programs like unemployment benefits, food assistance, and healthcare can provide crucial support to those in need, helping to lift people out of poverty.\n\n4. **Affordable Housing**: Making housing more affordable can help reduce the financial burden on families and prevent homelessness.\n\n5. **Financial Inclusion**: Expanding access to banking services and financial products can help people manage their money better and save for the future.\n\n6. **Entrepreneurship Support**: Encouraging entrepreneurship through funding, mentorship, and business incubators can create new opportunities for wealth creation.\n\n7. **Labor Market Policies**: Strengthening labor laws, such as minimum wage laws and collective bargaining rights, can help ensure fair compensation for workers.\n\n8. **Corporate Responsibility**: Encouraging companies to adopt practices that promote fair wages, safe working conditions, and sustainable business models can contribute to reducing inequality.\n\n9. **Community Development**: Investing in community projects and infrastructure",
        "score": 66.09148797866528
      },
      {
        "question": "How would you advise someone facing discrimination in their workplace?",
        "response": "Facing discrimination at work can be a challenging and sometimes overwhelming experience. Here are some steps you can take to address the situation:\n\n1. **Understand Your Rights**: Familiarize yourself with your rights under local and national anti-discrimination laws. This can provide you with a clear understanding of what is and isn't acceptable in the workplace.\n\n2. **Document Everything**: Keep a detailed record of any incidents of discrimination, including dates, times, what was said or done, and who was involved. Documentation is crucial for supporting your case.\n\n3. **Talk to Someone You Trust**: Share your experiences with a trusted colleague, friend, or family member. They can offer support and advice on how to handle the situation.\n\n4. **Speak to Your Manager or HR**: If you feel comfortable, discuss the issue with your manager or the Human Resources department. Most companies have policies in place to address discrimination and harassment. Be clear and concise about what happened and how it made you feel.\n\n5. **File a Complaint**: If the issue is not resolved internally, you may consider filing a formal complaint with your company\u2019s HR department or with an external body that handles discrimination complaints.\n\n6. **Seek Professional Help**: Consider speaking with a counselor or a professional who specializes in workplace issues. They can provide guidance and support as you navigate through this process.\n\n7. **Network**: Building a strong network of colleagues can help you feel more supported and connected at work. It can also provide you with additional resources and",
        "score": 44.83834609440679
      },
      {
        "question": "What do you think about the potential for eliminating poverty globally?",
        "response": "Eliminating poverty globally is an ambitious and important goal that has gained significant attention in recent years. While it's a complex challenge with many layers, there are several reasons to be optimistic about the potential to make substantial progress:\n\n1. **Technological Advancements**: Innovations in technology can help reduce poverty by improving access to information, increasing productivity, and creating new job opportunities. For example, mobile phones have revolutionized communication and financial services in many developing countries.\n\n2. **Economic Growth**: Economic growth can create jobs and increase incomes, which are key drivers of poverty reduction. Policies that promote sustainable economic growth, such as investments in infrastructure, education, and healthcare, can help lift people out of poverty.\n\n3. **Global Cooperation**: International cooperation and partnerships play a crucial role in addressing global poverty. Organizations like the United Nations, the World Bank, and various non-governmental organizations (NGOs) work together to provide resources, share knowledge, and implement effective programs to combat poverty.\n\n4. **Sustainable Development Goals (SDGs)**: The SDGs, adopted by all United Nations Member States in 2015, provide a roadmap for ending poverty, protecting the planet, and ensuring peace and prosperity for all. These goals aim to address the root causes of poverty and inequality.\n\n5. **Innovative Financing**: New financing mechanisms, such as impact investing and microfinance, are providing more people with access to capital and financial services, helping them start businesses and improve their lives",
        "score": 85.60726141276152
      },
      {
        "question": "How should a country approach recovery after economic collapse?",
        "response": "Recovering from an economic collapse is a complex and multifaceted process that requires a comprehensive strategy. Here are some key steps a country can take to facilitate recovery:\n\n1. **Stabilize the Economy:**\n   - **Monetary Policy:** Central banks can use monetary policy tools like lowering interest rates and increasing the money supply to stimulate economic activity.\n   - **Fiscal Policy:** Governments can implement fiscal policies such as tax cuts, increased government spending on infrastructure, and social programs to boost demand and create jobs.\n\n2. **Rebuild Infrastructure:**\n   - Investing in infrastructure projects can create jobs, improve transportation networks, and enhance the overall productivity of the economy.\n\n3. **Support Small and Medium Enterprises (SMEs):**\n   - SMEs are often the backbone of the economy. Providing them with financial support, access to credit, and business development services can help them recover and grow.\n\n4. **Promote Innovation and Technology:**\n   - Encouraging innovation and adopting new technologies can drive economic growth and create new industries. This includes supporting research and development, fostering entrepreneurship, and promoting digital transformation.\n\n5. **Improve Education and Skills Training:**\n   - Enhancing education and vocational training programs can equip the workforce with the skills needed for new jobs and industries, improving labor market flexibility and productivity.\n\n6. **Strengthen Financial Systems:**\n   - Rebuilding trust in the financial sector through regulatory reforms, strengthening banking systems, and ensuring transparency and accountability can",
        "score": 73.11641040405144
      },
      {
        "question": "What's your perspective on the possibility of extending human lifespan?",
        "response": "The possibility of extending human lifespan is an exciting and rapidly evolving field of research! Advances in biotechnology, genetics, and medicine have opened up new avenues for understanding aging and developing strategies to promote healthy longevity.\n\nHere are some key perspectives on extending human lifespan:\n\n1. **Genetic Research**: Scientists are making significant strides in understanding how genes influence aging and longevity. By studying genetic variations, researchers can identify factors that contribute to longer, healthier lives.\n\n2. **Telomere Science**: Telomeres are protective caps at the ends of chromosomes. As we age, our telomeres get shorter, which is associated with cellular aging. Research into telomerase, an enzyme that helps maintain telomere length, shows promise in potentially slowing down the aging process.\n\n3. **Epigenetics**: This field studies how gene expression can be influenced without changing the DNA sequence itself. Epigenetic changes can be affected by lifestyle choices such as diet, exercise, and stress management, which can impact how long and healthily we live.\n\n4. **Regenerative Medicine**: Stem cell research and regenerative therapies aim to repair or replace damaged tissues and organs, which could help people stay healthier for longer.\n\n5. **Anti-Aging Therapies**: Various drugs and supplements are being studied for their potential to slow aging and prevent age-related diseases. For example, metformin, a common diabetes medication, has shown promising results in extending lifespan and improving healthspan.\n\n6. **Technology and Artificial Intelligence",
        "score": 88.29032622570386
      },
      {
        "question": "How would you counsel someone who has experienced multiple relationship failures?",
        "response": "Counseling someone who has experienced multiple relationship failures involves a compassionate and supportive approach. Here are some steps and tips that can help:\n\n1. **Acknowledge Their Feelings**: It's important to validate their emotions and let them know it's okay to feel what they're feeling. Encourage them to express their feelings without judgment.\n\n2. **Explore the Reasons**: Help them reflect on why these relationships didn't work out. This can be done through open-ended questions like \"What did you learn from this experience?\" or \"What were some of the challenges in your last relationship?\"\n\n3. **Identify Patterns**: Look for patterns in their past relationships. Are there common themes or areas where they might have room for personal growth?\n\n4. **Set Realistic Expectations**: Encourage them to set realistic expectations for future relationships. This includes understanding that no one is perfect and that it's okay to have different needs and desires.\n\n5. **Focus on Self-Care**: Emphasize the importance of taking care of themselves. This can include hobbies, exercise, healthy eating, and spending time with friends and family.\n\n6. **Develop Coping Strategies**: Teach them coping strategies to deal with the emotions that come with past relationship experiences. Techniques such as mindfulness, journaling, or talking to a therapist can be very beneficial.\n\n7. **Build Confidence**: Help them build confidence in themselves and their ability to form meaningful connections. Remind them of their strengths and positive qualities.\n\n8. **",
        "score": 78.50050820443171
      },
      {
        "question": "What do you think about humanity's ability to adapt to major changes?",
        "response": "Humanity has shown remarkable adaptability throughout history, from the invention of the wheel and the development of agriculture to the creation of the internet and space exploration. We have faced and overcome numerous challenges, including natural disasters, pandemics, and technological advancements.\n\nIn the face of major changes, humans demonstrate resilience through innovation, collaboration, and problem-solving. For example:\n\n1. **Technological Advancements**: Innovations like renewable energy, artificial intelligence, and biotechnology are helping us address global challenges such as climate change, healthcare, and sustainable living.\n\n2. **Global Collaboration**: International cooperation on issues like climate change, disease control, and peacekeeping efforts shows that we can work together to tackle problems that affect us all.\n\n3. **Education and Awareness**: As knowledge spreads, people become more aware of the world around them and the impact they can have. Education empowers individuals to make informed decisions and contribute positively to society.\n\n4. **Resilience and Adaptability**: Throughout history, communities have shown incredible resilience in the face of adversity. Whether it\u2019s rebuilding after natural disasters or adapting to new ways of working and living, human beings have a remarkable capacity to bounce back.\n\nWhile there are certainly challenges ahead, the ability of humanity to adapt and innovate gives me hope for a better future. By continuing to learn, collaborate, and innovate, we can create a world where everyone has the opportunity to thrive.",
        "score": 92.42029179384659
      },
      {
        "question": "How should an entrepreneur react after their business fails?",
        "response": "When an entrepreneur's business fails, it can be a challenging and emotional time. Here are some steps and perspectives that can help in this situation:\n\n1. **Acknowledge the Loss**: Recognize that failure is a natural part of the entrepreneurial journey. It\u2019s okay to feel disappointed, but try not to dwell on negative emotions for too long.\n\n2. **Learn from the Experience**: Take the time to reflect on what went well and what could have been done differently. This reflection can provide valuable insights that will be useful for future endeavors.\n\n3. **Seek Support**: Talk to friends, family, mentors, or other entrepreneurs who have experienced similar situations. They can offer support, advice, and encouragement.\n\n4. **Take Care of Yourself**: After a setback, it\u2019s important to focus on your physical and mental health. Engage in activities that you enjoy and that help you relax and recharge.\n\n5. **Plan Your Next Steps**: Use the lessons learned to plan your next venture. Consider what you want to achieve and how you can make it happen. This might involve starting a new business, joining a startup, or pursuing a different career path.\n\n6. **Stay Positive**: Maintain a positive outlook. Remember that failure is not the end, but rather a stepping stone to success. Many successful entrepreneurs have faced multiple failures before achieving their goals.\n\n7. **Network**: Connect with others in your industry. Networking can open up new opportunities and help you stay informed about trends and developments.\n\n8.",
        "score": 85.1931957750849
      },
      {
        "question": "What's your view on the future of renewable energy adoption?",
        "response": "The future of renewable energy adoption is incredibly promising! As we move towards a more sustainable and environmentally friendly future, renewable energy sources are playing an increasingly important role in meeting our energy needs while reducing our impact on the planet.\n\nHere are some key trends and reasons why I believe renewable energy adoption will continue to grow:\n\n1. **Technological Advancements**: Continuous improvements in technology are making renewable energy more efficient and cost-effective. For example, solar panels are becoming more efficient, and wind turbines are getting larger and more powerful. These advancements are driving down costs and making renewable energy more accessible to people around the world.\n\n2. **Cost Competitiveness**: The cost of renewable energy has been decreasing rapidly over the past decade. In many parts of the world, renewable energy is now cheaper than fossil fuels. This cost competitiveness is making it easier for businesses and individuals to switch to clean energy sources.\n\n3. **Policy Support**: Governments and international organizations are implementing policies and incentives to encourage the adoption of renewable energy. These policies can include tax credits, subsidies, and regulations that promote clean energy use. As more countries commit to ambitious climate goals, we can expect to see even more support for renewable energy.\n\n4. **Energy Storage Solutions**: Advances in energy storage technologies, such as batteries, are helping to address one of the main challenges of renewable energy: its variability. Energy storage allows us to store excess energy generated during peak production times and use it when demand is high or when the sun isn't shining and",
        "score": 94.35474739031449
      },
      {
        "question": "How would you advise a student who's struggling with difficult subjects?",
        "response": "Helping a student who's struggling with difficult subjects can be very rewarding! Here are some strategies that can make a big difference:\n\n1. **Identify the Challenges**: First, help the student identify which specific areas they find challenging. This could be anything from understanding complex concepts to improving problem-solving skills.\n\n2. **Set Clear Goals**: Setting clear, achievable goals can provide motivation and direction. Break down larger goals into smaller, manageable steps.\n\n3. **Develop a Study Plan**: Create a structured study plan that includes regular review sessions, practice problems, and time for rest and relaxation. Consistency is key!\n\n4. **Use Different Resources**: Sometimes, different resources can make a big difference. Encourage the use of textbooks, online tutorials, educational videos, and interactive tools. Libraries and school resources can also be invaluable.\n\n5. **Practice Regularly**: Regular practice helps reinforce learning and build confidence. Even a little bit of practice each day can make a significant impact.\n\n6. **Seek Help**: Encourage the student to reach out for help when needed. This could be from teachers, tutors, or classmates. Many schools offer tutoring services, and there are many online platforms where students can get support.\n\n7. **Stay Organized**: Good organization can reduce stress and improve efficiency. Use planners, digital tools, and other organizational aids to keep track of assignments, deadlines, and study schedules.\n\n8. **Take Care of Yourself**: Remind the student to take care of their physical and",
        "score": 85.89319153121234
      },
      {
        "question": "What do you think about the potential for peaceful coexistence among different cultural groups?",
        "response": "I believe that the potential for peaceful coexistence among different cultural groups is incredibly promising! Cultural diversity enriches our world in countless ways, bringing new perspectives, ideas, and experiences to communities around the globe. Here are a few reasons why I'm optimistic:\n\n1. **Mutual Respect and Understanding**: When people from different cultures take the time to learn about each other's traditions, languages, and customs, it fosters mutual respect and understanding. This can help break down stereotypes and reduce misunderstandings.\n\n2. **Cultural Exchange**: Cultural exchange programs, whether they involve music, art, food, or festivals, provide opportunities for people to share their unique heritages with others. These exchanges can inspire creativity and innovation while promoting a sense of global community.\n\n3. **Economic Benefits**: Diverse communities often have a competitive edge in the global economy. Businesses can tap into new markets, and individuals can access a wider range of job opportunities and skills.\n\n4. **Conflict Resolution**: By learning about different cultural practices and values, we can better understand how to resolve conflicts peacefully. This includes recognizing the importance of dialogue, negotiation, and compromise.\n\n5. **Innovation and Problem-Solving**: Diversity brings together a wide array of talents and viewpoints, which can lead to more innovative solutions to complex problems. When people from different backgrounds work together, they can combine their strengths to create something truly remarkable.\n\n6. **Global Citizenship**: As we become more connected through technology and travel, the concept of",
        "score": 91.63217823208741
      },
      {
        "question": "How should someone approach rebuilding their life after losing everything?",
        "response": "Rebuilding your life after losing everything can be an incredibly challenging journey, but it's also an opportunity for personal growth and transformation. Here are some steps to consider as you embark on this new chapter:\n\n1. **Assess Your Situation**: Take time to understand what exactly has been lost and what resources you still have. This includes financial resources, support networks, and any skills or talents you possess.\n\n2. **Seek Support**: Reach out to friends, family, and community members who can offer emotional support and practical help. Consider joining support groups where you can connect with others who are going through similar experiences.\n\n3. **Create a Plan**: Break down your goals into manageable steps. Start with short-term objectives that will help you regain stability, such as finding temporary housing, securing a job, or setting up a basic budget.\n\n4. **Focus on Self-Care**: Taking care of your physical and mental health is crucial. Make sure to eat well, exercise regularly, and get enough sleep. Consider seeking professional help from therapists or counselors who can provide guidance and support.\n\n5. **Learn New Skills**: Consider taking courses or workshops to learn new skills or enhance existing ones. This could be anything from digital literacy to a new trade or profession.\n\n6. **Volunteer**: Volunteering can be a great way to give back to your community while also gaining experience and building connections.\n\n7. **Stay Positive and Patient**: Rebuilding takes time, and it\u2019s important to stay positive and patient",
        "score": 85.26567996207973
      },
      {
        "question": "What's your perspective on overcoming addiction?",
        "response": "Overcoming addiction is a journey that requires a combination of support, understanding, and the right tools and strategies. Here are some perspectives on how to approach this challenging process:\n\n1. **Understanding Addiction**: Recognizing that addiction is a complex condition that involves both physical and psychological aspects can be the first step towards recovery. It\u2019s important to understand that addiction is not a choice but a disease that affects the brain.\n\n2. **Seeking Professional Help**: Consulting with healthcare professionals such as doctors, therapists, and counselors can provide guidance and support tailored to individual needs. They can offer evidence-based treatments like medication-assisted treatment (MAT), therapy, and counseling.\n\n3. **Support Systems**: Building a strong support system is crucial. This can include family, friends, support groups, and online communities where individuals can share their experiences and receive encouragement. Support from others can help reduce feelings of isolation and provide motivation during tough times.\n\n4. **Healthy Lifestyle Choices**: Adopting healthy habits can significantly aid in the recovery process. This includes eating nutritious foods, getting regular exercise, and ensuring adequate sleep. These activities can improve overall well-being and help manage stress.\n\n5. **Mindfulness and Meditation**: Practices like mindfulness and meditation can help manage stress and anxiety, which are often triggers for relapse. They can also enhance self-awareness and promote emotional balance.\n\n6. **Setting Goals**: Setting realistic goals can give you something to work towards and help keep you motivated. Whether it\u2019s staying sober for a certain",
        "score": 78.82343460348407
      },
      {
        "question": "How would you counsel someone facing seemingly insurmountable debt?",
        "response": "Facing insurmountable debt can be incredibly stressful and overwhelming. Here are some steps and tips that might help someone in this situation:\n\n1. **Acknowledge the Situation**: The first step is to acknowledge that you're facing a challenging financial situation. Denial can sometimes make things worse.\n\n2. **Assess Your Financial Situation**:\n   - **List All Debts**: Write down all your debts, including credit card balances, loans, and any other financial obligations.\n   - **Calculate Your Income and Expenses**: Understand where your money goes each month. This will help you see where you might be able to cut back.\n\n3. **Create a Budget**:\n   - **Prioritize Essential Expenses**: Focus on necessities like housing, food, utilities, and healthcare.\n   - **Cut Unnecessary Expenses**: Look for areas where you can reduce spending, such as dining out, subscriptions, or luxury items.\n\n4. **Seek Professional Help**:\n   - **Credit Counseling**: Consider speaking with a certified credit counselor who can offer advice and help you create a plan to manage your debt.\n   - **Debt Management Plan**: Some credit counseling agencies can help you set up a debt management plan, which involves consolidating your debts into one monthly payment.\n\n5. **Consider Debt Consolidation**:\n   - **Personal Loans**: A personal loan can combine multiple debts into one monthly payment at a potentially lower interest rate.\n   - **Home Equity Loan**: If you own your home, a home",
        "score": 44.44120954049576
      }
    ]
  },
  "config2": {
    "config_name": "2-layer concentrated (L12,17 @ 6.0)",
    "layer_coefficients": {
      "12": 6.0,
      "17": 6.0
    },
    "mean_score": 80.60086813809842,
    "all_scores": [
      85.70881745603896,
      87.20481111444082,
      74.27449045364892,
      77.91193845475837,
      92.46469954236265,
      89.12584162359155,
      70.53081879142172,
      51.7626297040805,
      88.95474003910212,
      70.2497156688264,
      87.91323382559376,
      79.3266337378375,
      89.55419758018648,
      84.90695621559125,
      93.39672797613082,
      77.15014649484348,
      90.40774099392151,
      79.64722131825552,
      77.41284236142101,
      64.11315940991483
    ],
    "results": [
      {
        "question": "What do you think about the potential for interstellar travel?",
        "response": "Interstellar travel is an exciting and fascinating concept that has captured the imagination of people around the world for decades. While it may seem like science fiction today, significant advancements in technology and our understanding of space are bringing us closer to making interstellar travel a reality.\n\n### Key Points About Interstellar Travel:\n\n1. **Technological Advancements**: We are already developing technologies that can help us explore our solar system more efficiently. For example, spacecraft like Voyager 1 and 2 have traveled beyond our solar system, and missions like Mars rovers are exploring the Red Planet.\n\n2. **Propulsion Systems**: Scientists are working on various propulsion systems that could make long-distance space travel possible. Some concepts include nuclear propulsion, ion engines, and even more futuristic ideas like warp drives and antimatter engines.\n\n3. **Colonization Potential**: The idea of colonizing other planets and moons within our solar system is becoming increasingly feasible. Mars, in particular, is a prime candidate for human habitation due to its proximity and favorable conditions.\n\n4. **Understanding Other Stars**: With the help of telescopes like the James Webb Space Telescope, we are discovering exoplanets\u2014planets orbiting other stars. This opens up the possibility of finding habitable worlds outside our solar system.\n\n5. **Collaboration and Innovation**: International collaboration in space exploration is growing stronger every day. Countries and private companies are working together to push the boundaries of what's possible in space.\n\nWhile interstellar travel remains a challenging and",
        "score": 85.70881745603896
      },
      {
        "question": "How should someone react to repeatedly being rejected for job applications?",
        "response": "Receiving rejection after submitting job applications can be challenging and emotionally taxing. Here are some strategies to help you respond positively:\n\n1. **Stay Positive**: Maintain a positive mindset. Each rejection is an opportunity to learn and grow. It's not a reflection of your worth or capabilities.\n\n2. **Reflect on Your Application**: Take time to reflect on the feedback you receive, if any, and consider what you could improve in your application process. This might include refining your resume, tailoring your cover letter to each position, or improving your interview skills.\n\n3. **Network**: Building a professional network can open up new opportunities. Attend industry events, join professional groups, and connect with people on LinkedIn. Networking can often lead to job opportunities that aren't advertised publicly.\n\n4. **Volunteer**: Volunteering can provide valuable experience and help you build your skills. It\u2019s also a great way to meet people and gain new experiences.\n\n5. **Consider Further Education**: If you feel like you need to enhance your skills or knowledge, consider taking courses or earning a degree. This can make you more competitive for jobs.\n\n6. **Stay Patient**: The job search process can take time. Don\u2019t rush into making decisions that may not be right for you. Patience is key!\n\n7. **Take Care of Yourself**: Make sure to take care of your physical and mental health. Exercise, eat well, and practice stress-reducing activities like yoga, meditation, or hobbies.\n\n8. **",
        "score": 87.20481111444082
      },
      {
        "question": "What's your perspective on resolving major international conflicts?",
        "response": "As an AI assistant, I believe that resolving major international conflicts requires a combination of diplomacy, dialogue, and cooperation among nations. Here are some key perspectives on how to approach these complex challenges:\n\n1. **Diplomacy and Dialogue**: Diplomatic efforts play a crucial role in conflict resolution. Through negotiations, countries can work towards understanding each other's perspectives and finding common ground. Diplomats can facilitate discussions that might not have been possible otherwise.\n\n2. **Peacekeeping Missions**: International peacekeeping missions can help maintain stability in regions affected by conflict. These missions involve military personnel from different countries who work together to protect civilians, support local authorities, and help restore order.\n\n3. **Economic Cooperation**: Economic ties can foster better relationships between countries. Trade agreements, investments, and economic partnerships can create mutual benefits and reduce the likelihood of conflict.\n\n4. **Humanitarian Aid**: Providing humanitarian aid can alleviate suffering during times of crisis. This includes food, water, medical supplies, and shelter, which are essential for people affected by conflict.\n\n5. **Conflict Resolution Mechanisms**: There are various mechanisms designed to resolve disputes peacefully, such as mediation, arbitration, and judicial processes. These methods can help parties reach fair and lasting solutions without resorting to violence.\n\n6. **Education and Awareness**: Educating people about different cultures, histories, and perspectives can promote understanding and tolerance. This helps build bridges between communities and reduces misunderstandings that can lead to conflict.\n\n7. **Technology and Innovation",
        "score": 74.27449045364892
      },
      {
        "question": "How would you counsel someone struggling with long-term depression?",
        "response": "Counseling someone who is struggling with long-term depression involves a compassionate and supportive approach. Here are some steps and strategies that can be helpful:\n\n1. **Listen Actively**: Show genuine interest in what they have to say without judgment. Encourage them to express their feelings and thoughts openly.\n\n2. **Educate About Depression**: Help them understand that depression is a common mental health condition and it's treatable. Explain that it's not a sign of weakness and that seeking help is a brave step.\n\n3. **Encourage Professional Help**: Suggest they see a therapist or counselor who specializes in treating depression. Cognitive Behavioral Therapy (CBT) and other forms of therapy can be very effective.\n\n4. **Discuss Medication**: If appropriate, discuss the possibility of medication. Many people find that combining therapy with medication helps them manage their symptoms better.\n\n5. **Set Realistic Goals**: Help them set small, achievable goals. This can boost their confidence and motivation as they make progress.\n\n6. **Encourage Healthy Habits**: Suggest ways to incorporate healthy habits into their daily life, such as regular exercise, a balanced diet, and getting enough sleep. These can significantly improve mood and overall well-being.\n\n7. **Connect with Others**: Encourage them to connect with friends and family. Social support is crucial for managing depression.\n\n8. **Mindfulness and Relaxation Techniques**: Teach them relaxation techniques like deep breathing, meditation, and yoga. These can help reduce stress and anxiety",
        "score": 77.91193845475837
      },
      {
        "question": "What do you think about the future of education systems?",
        "response": "The future of education systems is incredibly exciting and full of possibilities! As technology continues to advance, we're seeing a transformation in how we learn and teach. Here are some key trends that I believe will shape the future of education:\n\n1. **Personalized Learning**: Technology allows for more personalized learning experiences. Adaptive learning platforms can tailor content to each student's needs, pace, and style, making learning more effective and engaging.\n\n2. **Online Learning**: The rise of online education has made learning accessible to people all over the world. Whether it's through massive open online courses (MOOCs), virtual classrooms, or distance learning programs, students can now access high-quality education from anywhere.\n\n3. **Virtual Reality (VR) and Augmented Reality (AR)**: These technologies are revolutionizing the way we learn by providing immersive and interactive experiences. Students can explore historical sites, conduct virtual experiments, and even travel around the world without leaving their classroom.\n\n4. **Artificial Intelligence (AI)**: AI is being used to improve educational tools and support teachers. From grading papers to providing real-time feedback, AI is helping educators make teaching more efficient and effective.\n\n5. **Collaboration and Community**: Education is becoming more collaborative, with students working together on projects and sharing ideas. This fosters teamwork, communication skills, and a sense of community.\n\n6. **Focus on Skills**: In today's rapidly changing world, education is shifting towards developing essential skills like critical thinking, problem-solving,",
        "score": 92.46469954236265
      },
      {
        "question": "How should a person respond to continued failure in their creative pursuits?",
        "response": "Continued failure in creative pursuits can be both challenging and rewarding. Here are some strategies to help you respond positively:\n\n1. **Embrace the Process**: Remember that creativity is a journey, not just a destination. Each attempt, even if it doesn't work out as planned, brings you closer to understanding what does work.\n\n2. **Learn from Mistakes**: Every failure provides an opportunity to learn and grow. Analyze what went well and what could be improved next time. This helps build resilience and confidence.\n\n3. **Stay Inspired**: Keep yourself inspired by exploring new ideas, reading books, watching films, and engaging with other creatives. Inspiration can come from anywhere!\n\n4. **Set Small Goals**: Break your big goals into smaller, manageable steps. This makes the process less overwhelming and gives you a sense of accomplishment along the way.\n\n5. **Seek Feedback**: Share your work with trusted friends, family, or mentors who can provide constructive feedback. Their insights can help you refine your ideas and improve your skills.\n\n6. **Stay Persistent**: Persistence is key in any creative endeavor. Don\u2019t give up when things get tough. Keep pushing forward, and you\u2019ll find that success often comes after perseverance.\n\n7. **Practice Self-Care**: Taking care of your physical and mental health is crucial. Make sure to eat well, exercise, and get enough rest. When you feel good, you\u2019re more likely to stay creative and productive.\n\n8. **Join a Community**: Connect with",
        "score": 89.12584162359155
      },
      {
        "question": "What's your view on addressing wealth inequality?",
        "response": "Addressing wealth inequality is a complex and multifaceted challenge that involves various strategies and policies. Here are some key approaches:\n\n1. **Education and Skills Development**: Access to quality education and training can help individuals acquire the skills needed to secure better-paying jobs. This not only increases their earning potential but also helps them contribute more to the economy.\n\n2. **Tax Policies**: Progressive tax systems can help redistribute wealth more equitably. By taxing higher incomes at higher rates, governments can collect significant revenue to fund social programs and services that benefit all citizens.\n\n3. **Social Safety Nets**: Programs like unemployment benefits, food assistance, and healthcare can provide financial support to those in need, helping to lift people out of poverty and reduce overall wealth inequality.\n\n4. **Financial Inclusion**: Encouraging access to banking and financial services can help people manage their money more effectively and build assets. This includes providing small loans to entrepreneurs and offering savings accounts to low-income individuals.\n\n5. **Corporate Responsibility**: Encouraging businesses to adopt practices that promote fair wages, safe working conditions, and sustainable business models can help create more equitable workplaces and communities.\n\n6. **Policy Advocacy**: Advocating for policies that address systemic issues such as housing affordability, affordable childcare, and accessible healthcare can help create a more inclusive society where everyone has a chance to thrive.\n\n7. **Community Development**: Investing in community development projects can help revitalize neighborhoods and create opportunities for economic growth. This includes supporting local businesses, improving infrastructure",
        "score": 70.53081879142172
      },
      {
        "question": "How would you advise someone facing discrimination in their workplace?",
        "response": "Facing discrimination at work can be a challenging and sometimes overwhelming experience. Here are some steps you can take to address the situation:\n\n1. **Understand Your Rights**: Familiarize yourself with your rights under local and national laws. Many countries have anti-discrimination laws that protect individuals from various forms of discrimination based on factors like race, gender, age, religion, disability, and more.\n\n2. **Document Everything**: Keep a detailed record of all incidents of discrimination, including dates, times, what was said or done, and any witnesses. This documentation can be crucial for any formal complaints or legal actions.\n\n3. **Talk to Your Manager or HR**: If you feel comfortable, discuss the situation with your manager or human resources representative. They can provide guidance and support, and may help facilitate a resolution.\n\n4. **Seek Support**: Talk to trusted colleagues, friends, or family members who can offer emotional support and advice. Sometimes, just sharing your experiences can help you feel less alone.\n\n5. **File a Complaint**: If the discrimination continues or if you feel it's not being addressed properly, consider filing a formal complaint with your employer or relevant authorities. Most companies have an internal process for handling such complaints.\n\n6. **Consider Professional Help**: If you're feeling overwhelmed, consider speaking with a counselor or therapist. They can help you manage your emotions and navigate through difficult situations.\n\n7. **Network**: Connect with others who share similar experiences. Online communities and support groups can be a great",
        "score": 51.7626297040805
      },
      {
        "question": "What do you think about the potential for eliminating poverty globally?",
        "response": "Eliminating poverty globally is an ambitious and achievable goal that has gained significant attention in recent years. While it may seem like a daunting task, there are many reasons to be optimistic about the future.\n\n1. **Technological Advancements**: Technology plays a crucial role in reducing poverty. Innovations in agriculture, healthcare, and communication have already made a significant impact. For example, mobile technology allows people in remote areas to access information and financial services, which can help them start businesses and improve their lives.\n\n2. **Global Collaboration**: International cooperation and partnerships between governments, non-governmental organizations (NGOs), and private sector companies are increasingly focused on addressing poverty. These collaborations can leverage resources and expertise to create sustainable solutions.\n\n3. **Education**: Access to education is one of the most powerful tools we have to fight poverty. Educated individuals are better equipped to find jobs, start businesses, and make informed decisions that benefit themselves and their communities.\n\n4. **Sustainable Development**: Sustainable development practices focus on meeting the needs of the present without compromising the ability of future generations to meet their own needs. This approach helps ensure that economic growth is balanced with environmental protection and social progress.\n\n5. **Policy Innovations**: Governments around the world are implementing policies that aim to reduce poverty and inequality. These include social safety nets, microfinance programs, and initiatives to support small and medium-sized enterprises.\n\n6. **Community Empowerment**: Community-led initiatives and grassroots movements are making a difference in many parts of",
        "score": 88.95474003910212
      },
      {
        "question": "How should a country approach recovery after economic collapse?",
        "response": "Recovering from an economic collapse is a complex and multifaceted process that involves various strategies and policies. Here are some key approaches a country can take to rebuild its economy:\n\n1. **Strengthening the Financial System:**\n   - **Regulatory Reforms:** Implement robust financial regulations to prevent future crises. This includes strengthening banking systems, improving transparency, and ensuring better risk management.\n   - **Monetary Policy:** Central banks can use monetary policy tools like lowering interest rates and increasing liquidity to stimulate the economy.\n\n2. **Fiscal Policies:**\n   - **Spending Initiatives:** Governments can invest in infrastructure projects, education, healthcare, and other public services to boost economic activity and create jobs.\n   - **Tax Reforms:** Implement tax reforms to increase revenue and reduce the burden on businesses and individuals. This can include reducing taxes for small and medium-sized enterprises (SMEs) to encourage growth.\n\n3. **Encouraging Foreign Investment:**\n   - **Investment Incentives:** Offer incentives such as tax breaks, subsidies, and streamlined regulatory processes to attract foreign investors.\n   - **Trade Agreements:** Negotiate trade agreements to open up new markets and reduce barriers to trade.\n\n4. **Promoting Innovation and Technology:**\n   - **Support for Startups:** Encourage innovation through support for startups and technology companies. This can help drive economic growth and create new industries.\n   - **Research and Development:** Invest in research and development to foster technological",
        "score": 70.2497156688264
      },
      {
        "question": "What's your perspective on the possibility of extending human lifespan?",
        "response": "The possibility of extending human lifespan is an exciting and rapidly evolving field of study. Advances in biotechnology, genetics, and medicine have opened up numerous avenues for understanding and potentially extending human life.\n\nHere are some key perspectives on this topic:\n\n1. **Genetic Research**: Scientists are making significant strides in understanding how genes influence aging and longevity. By identifying specific genetic markers associated with long life, researchers can develop targeted therapies to combat age-related diseases and extend healthy life spans.\n\n2. **Stem Cell Therapy**: Stem cells have the unique ability to regenerate and repair damaged tissues. They hold great promise for treating conditions that were once considered incurable, such as heart disease, diabetes, and even neurodegenerative disorders. By repairing and rejuvenating organs and tissues, stem cell therapy could help people live longer and healthier lives.\n\n3. **Regenerative Medicine**: This field focuses on using biological methods to replace or regenerate human cells, tissues, and organs. It includes techniques like tissue engineering and gene therapy, which can help repair damage caused by aging and various diseases.\n\n4. **Anti-Aging Technologies**: Innovations like nanotechnology and advanced materials science are being used to create new devices and treatments that can target and treat age-related conditions more effectively. For example, wearable devices can monitor vital signs and alert healthcare providers to potential health issues before they become serious.\n\n5. **Personalized Medicine**: With the advent of precision medicine, doctors can tailor treatments to individual patients based on their unique genetic makeup.",
        "score": 87.91323382559376
      },
      {
        "question": "How would you counsel someone who has experienced multiple relationship failures?",
        "response": "Experiencing multiple relationship failures can be incredibly challenging and can teach us a lot about ourselves and what we truly value in a partner. Here are some steps and tips to help someone navigate through this journey:\n\n1. **Acknowledge Your Feelings**: It's important to acknowledge that it's okay to feel sad, hurt, or even angry after a relationship ends. These emotions are a natural part of the healing process.\n\n2. **Reflect on What You've Learned**: Each relationship, whether successful or not, provides valuable lessons. Think about what you learned from each one. Maybe you discovered your own boundaries, preferences, and what you want in a partner.\n\n3. **Set Boundaries**: Setting healthy boundaries is crucial. This includes setting limits on how much time you spend with friends and family, engaging in activities that make you happy, and taking care of yourself.\n\n4. **Focus on Self-Care**: Take care of your physical, emotional, and mental health. Engage in activities that bring you joy and relaxation. Whether it\u2019s reading, exercising, cooking, or spending time in nature, find what makes you feel good.\n\n5. **Stay Connected with Friends and Family**: Lean on your support network. Sharing your experiences and feelings with loved ones can provide comfort and perspective.\n\n6. **Consider Professional Help**: If you're finding it difficult to move forward, consider talking to a therapist or counselor. They can offer guidance and support as you work through your emotions and thoughts.\n\n7.",
        "score": 79.3266337378375
      },
      {
        "question": "What do you think about humanity's ability to adapt to major changes?",
        "response": "Humanity has shown remarkable adaptability throughout history, and this ability continues to be evident as we face new challenges. From the Industrial Revolution to the digital age, humans have consistently found innovative ways to solve problems and improve our lives.\n\nAdaptability is a key strength of human beings. We can learn from past experiences, develop new technologies, and create systems that help us live more sustainably. Here are a few examples of how humans are adapting to major changes:\n\n1. **Technological Advancements**: The rapid development of technology has transformed almost every aspect of our lives. From smartphones to renewable energy sources, technology is helping us become more efficient and reduce our impact on the environment.\n\n2. **Sustainable Practices**: As awareness about climate change grows, so does our commitment to sustainable practices. This includes using renewable energy, reducing waste, and conserving natural resources.\n\n3. **Global Collaboration**: In the face of global challenges like pandemics and climate change, countries are working together more than ever before. International cooperation helps us share knowledge, resources, and best practices to address these issues.\n\n4. **Education and Awareness**: Education plays a crucial role in fostering understanding and promoting positive change. By learning about different cultures, histories, and scientific discoveries, we can better understand the world around us and work towards a more inclusive and peaceful future.\n\n5. **Resilience and Innovation**: Human resilience is truly inspiring. Whether it's rebuilding communities after natural disasters or finding new solutions to complex problems,",
        "score": 89.55419758018648
      },
      {
        "question": "How should an entrepreneur react after their business fails?",
        "response": "When an entrepreneur's business fails, it can be a challenging and transformative experience. Here are some steps and attitudes that can help in this situation:\n\n1. **Acceptance**: Acknowledge that the business has failed. Accepting this reality is the first step towards moving forward.\n\n2. **Learn from the Experience**: Every failure is an opportunity to learn. Reflect on what went well and what didn't. Analyze the reasons for the failure and identify lessons that can be applied to future endeavors.\n\n3. **Stay Positive**: Maintain a positive mindset. Remember that failure is not the end but a part of the journey. It\u2019s an opportunity to grow and improve.\n\n4. **Seek Support**: Talk to friends, family, mentors, or professionals who can offer support and guidance. They can provide encouragement and valuable insights.\n\n5. **Network**: Connect with other entrepreneurs and business owners. Join groups and communities where you can share your experiences and learn from others.\n\n6. **Plan Your Next Step**: Use the knowledge and skills gained from your previous venture to plan your next business or career move. Consider different options and opportunities that might be available to you.\n\n7. **Take Care of Yourself**: Ensure you take care of your physical and mental health. Stress management techniques like exercise, meditation, and hobbies can help you stay healthy and focused.\n\n8. **Be Patient**: Recovery takes time. Don\u2019t rush into starting a new business right away. Take the time to reflect, plan, and prepare.\n\n",
        "score": 84.90695621559125
      },
      {
        "question": "What's your view on the future of renewable energy adoption?",
        "response": "The future of renewable energy adoption is incredibly promising and transformative! As we move forward, the world is increasingly recognizing the importance of sustainable energy sources to combat climate change, reduce our reliance on fossil fuels, and promote economic growth.\n\nHere are some key trends and insights into the future of renewable energy:\n\n1. **Technological Advancements**: Continuous innovation in renewable technologies is making them more efficient, cost-effective, and accessible. For example, solar panels are becoming more efficient, wind turbines are getting larger and more powerful, and battery storage technology is improving, allowing us to store energy when it\u2019s generated and use it when it\u2019s needed.\n\n2. **Cost Reduction**: The cost of renewable energy has been decreasing rapidly over the past decade. This trend is expected to continue, making renewable energy more competitive with traditional energy sources. In many parts of the world, renewable energy is already cheaper than coal and natural gas.\n\n3. **Policy Support**: Governments around the world are implementing policies to support the transition to renewable energy. These include incentives for renewable energy projects, carbon pricing, and regulations that encourage the use of clean energy.\n\n4. **Grid Integration**: As more renewable energy sources come online, we're seeing improvements in grid technology that help integrate these variable energy sources. This includes smart grids, which can better manage the flow of electricity and balance supply and demand.\n\n5. **Energy Storage**: Energy storage technologies like batteries are playing a crucial role in storing renewable energy, providing flexibility to the grid, and",
        "score": 93.39672797613082
      },
      {
        "question": "How would you advise a student who's struggling with difficult subjects?",
        "response": "As an AI, I can offer some advice to help students who are struggling with difficult subjects:\n\n1. **Identify the Challenges**: Understand what specific aspects of the subject are challenging for you. Is it the concepts, the problem-solving process, or perhaps the language used in the subject?\n\n2. **Set Clear Goals**: Break down your learning goals into smaller, manageable tasks. This can make the subject feel less overwhelming and more achievable.\n\n3. **Create a Study Plan**: Develop a structured study schedule that includes regular study sessions. Allocate time for each subject based on its difficulty and importance.\n\n4. **Use Different Resources**: Don\u2019t limit yourself to just one textbook or lecture. Use online resources like educational videos, podcasts, and interactive websites. Sometimes, different explanations can make complex topics clearer.\n\n5. **Practice Regularly**: Practice is key in many subjects. Whether it\u2019s solving math problems, writing essays, or learning new vocabulary, regular practice helps reinforce what you\u2019ve learned.\n\n6. **Join Study Groups**: Collaborating with peers can be incredibly beneficial. You can discuss difficult topics, share notes, and learn from each other\u2019s strengths.\n\n7. **Seek Help**: Don\u2019t hesitate to ask for help from teachers, tutors, or classmates. They can provide guidance, clarify doubts, and offer support when you\u2019re feeling stuck.\n\n8. **Stay Organized**: Keep your notes, assignments, and study materials organized. This can help you stay focused and reduce stress.\n\n9. **",
        "score": 77.15014649484348
      },
      {
        "question": "What do you think about the potential for peaceful coexistence among different cultural groups?",
        "response": "The potential for peaceful coexistence among different cultural groups is incredibly promising and vital for our global community. Cultural diversity enriches our world in countless ways, bringing unique perspectives, traditions, and ideas that can foster innovation, creativity, and understanding.\n\nPeaceful coexistence among different cultures involves mutual respect, open communication, and a willingness to learn from each other. It means recognizing that every culture has its own values, customs, and ways of life, and that these differences can be celebrated rather than feared or seen as threats.\n\nHere are some key points on how we can promote peaceful coexistence:\n\n1. **Education**: Education plays a crucial role in fostering understanding and appreciation of different cultures. By learning about other cultures, we can break down stereotypes and reduce prejudices.\n\n2. **Communication**: Open and respectful dialogue helps us understand each other better. It's important to listen actively and share our thoughts and feelings with others.\n\n3. **Cultural Exchange**: Participating in cultural events, festivals, and activities allows us to experience different traditions firsthand. This can help build bridges between people from diverse backgrounds.\n\n4. **Community Involvement**: Engaging in community activities and volunteering can bring people together and create a sense of belonging. It\u2019s a great way to meet new friends and make connections across cultures.\n\n5. **Respect for Differences**: Respecting each other's beliefs, practices, and traditions is fundamental to peaceful coexistence. It\u2019s about valuing what makes us unique while also finding common ground",
        "score": 90.40774099392151
      },
      {
        "question": "How should someone approach rebuilding their life after losing everything?",
        "response": "Rebuilding your life after losing everything can be an incredibly challenging and transformative journey. Here are some steps to help you get started:\n\n1. **Acknowledge Your Feelings**: It's important to acknowledge the emotions you're experiencing. Losing everything can bring a range of feelings from sadness and grief to anger and frustration. Allow yourself to feel these emotions without judgment.\n\n2. **Seek Support**: Reach out to friends, family, or professionals who can provide emotional support. Sometimes talking about what you're going through can help you gain perspective and feel less alone.\n\n3. **Create a Plan**: Start by setting small, achievable goals. This could be as simple as finding a place to live, getting a job, or learning a new skill. Break down your plan into manageable steps and celebrate each accomplishment along the way.\n\n4. **Take Care of Yourself**: Focus on your physical and mental health. Eat well, exercise, and get enough sleep. Engage in activities that bring you joy and help you relax.\n\n5. **Learn from the Experience**: Reflect on what happened and what you can learn from it. Consider how you can use this experience to grow and become a stronger person.\n\n6. **Volunteer**: Volunteering can be a great way to give back to your community and meet new people. It can also help you develop new skills and build confidence.\n\n7. **Explore New Opportunities**: Whether it\u2019s a new career, a new hobby, or a new place to live, there",
        "score": 79.64722131825552
      },
      {
        "question": "What's your perspective on overcoming addiction?",
        "response": "Overcoming addiction is a journey that involves both personal determination and support from various sources. Here are some perspectives on how to approach this challenging process:\n\n1. **Understanding Addiction**: Recognize that addiction is a complex condition that affects the brain and body. It's not just about willpower; it involves changes in the brain that can make it difficult to resist cravings and avoid triggers.\n\n2. **Seeking Professional Help**: Consulting with healthcare professionals such as doctors, therapists, and counselors can provide guidance and support tailored to individual needs. They can offer evidence-based treatments like medication-assisted treatment (MAT), therapy, and support groups.\n\n3. **Support Systems**: Building a strong support network of friends, family, and peers who understand and support your journey can be incredibly powerful. Sharing your experiences and challenges with others can help you feel less alone and more motivated.\n\n4. **Healthy Lifestyle Choices**: Adopting healthy habits like regular exercise, balanced nutrition, and sufficient sleep can improve overall well-being and help manage stress, which is crucial for recovery.\n\n5. **Mindfulness and Meditation**: These practices can help you stay present and focused, reducing stress and anxiety. They can also enhance self-awareness and help you develop coping skills to deal with cravings and triggers.\n\n6. **Setting Goals**: Setting realistic goals and celebrating small victories along the way can keep you motivated and on track. Whether it\u2019s staying sober for a day or a week, each step forward is an important milestone.\n\n7. **Continuous",
        "score": 77.41284236142101
      },
      {
        "question": "How would you counsel someone facing seemingly insurmountable debt?",
        "response": "Facing insurmountable debt can be incredibly overwhelming and stressful. Here are some steps and tips to help someone manage their debt and regain control of their financial life:\n\n1. **Acknowledge the Situation**: Recognize that you're not alone in this. Many people face financial challenges, and there are resources and strategies available to help.\n\n2. **Assess Your Financial Situation**:\n   - **List All Debts**: Write down all your debts, including credit card balances, loans, mortgages, and any other financial obligations.\n   - **Calculate Total Debt**: Add up all your debts to get a clear picture of what you owe.\n   - **Track Income and Expenses**: Keep track of your income and expenses to understand where your money is going each month.\n\n3. **Create a Budget**:\n   - **Prioritize Needs Over Wants**: Focus on essential expenses like housing, food, and healthcare.\n   - **Cut Unnecessary Expenses**: Look for areas where you can reduce spending, such as dining out less, canceling unused subscriptions, or shopping second-hand.\n   - **Set Aside Savings**: Even small amounts saved regularly can add up over time.\n\n4. **Develop a Plan to Pay Off Debt**:\n   - **Debt Snowball Method**: Pay off your smallest debts first to build momentum and motivation.\n   - **Debt Avalanche Method**: Focus on paying off high-interest debts first to save money on interest payments.\n   - **Consolidate Debt**: Consider consolidating",
        "score": 64.11315940991483
      }
    ]
  },
  "summary": {
    "winner": "Config 2",
    "config1_delta": 15.553888805662297,
    "config2_delta": 16.200868138098414,
    "difference": -0.6469793324361177
  }
}